pybsh/__init__.py
pybsh-1.0.0.dist-info/METADATA
pybsh-1.0.0.dist-info/WHEEL
pybsh-1.0.0.dist-info/top_level.txt
pybsh-1.0.0.dist-info/RECORD
